{
  "athletico_pr": [
    {
      "name": "Mycael",
      "position": "GOL",
      "rating": 83,
      "age": 22
    },
    {
      "name": "Leonardo Derik",
      "position": "ZAG",
      "rating": 83,
      "age": 20
    },
    {
      "name": "Arthur Monteiro",
      "position": "ZAG",
      "rating": 83,
      "age": 16
    },
    {
      "name": "Juan Portilla",
      "position": "MEI",
      "rating": 83,
      "age": 27
    },
    {
      "name": "João Cruz",
      "position": "MEI",
      "rating": 83,
      "age": 20
    },
    {
      "name": "Kevin Viveros",
      "position": "ATA",
      "rating": 83,
      "age": 26
    },
    {
      "name": "Lucas Amorim",
      "position": "ATA",
      "rating": 83,
      "age": 20
    },
    {
      "name": "Juliano Santini",
      "position": "ATA",
      "rating": 83,
      "age": 19
    },
    {
      "name": "Jádson",
      "position": "MEI",
      "rating": 82,
      "age": 32
    },
    {
      "name": "Alejandro García",
      "position": "MEI",
      "rating": 81,
      "age": 25
    },
    {
      "name": "Chiqueti",
      "position": "MEI",
      "rating": 81,
      "age": 21
    },
    {
      "name": "Kauan Stabelini",
      "position": "MEI",
      "rating": 81,
      "age": 19
    },
    {
      "name": "Renan",
      "position": "ATA",
      "rating": 81,
      "age": 26
    },
    {
      "name": "Santos",
      "position": "GOL",
      "rating": 80,
      "age": 36
    },
    {
      "name": "Dudu",
      "position": "ZAG",
      "rating": 80,
      "age": 29
    },
    {
      "name": "Guilherme Back",
      "position": "MEI",
      "rating": 80,
      "age": 19
    },
    {
      "name": "Claudinho",
      "position": "ZAG",
      "rating": 79,
      "age": 20
    },
    {
      "name": "Diogo Riquelme",
      "position": "MEI",
      "rating": 79,
      "age": 21
    },
    {
      "name": "Benjamín Brito",
      "position": "MEI",
      "rating": 79,
      "age": 18
    },
    {
      "name": "Sorriso",
      "position": "ATA",
      "rating": 79,
      "age": 20
    },
    {
      "name": "Hayen Palacios",
      "position": "ZAG",
      "rating": 78,
      "age": 26
    },
    {
      "name": "Gastón Benavídez",
      "position": "ZAG",
      "rating": 78,
      "age": 30
    },
    {
      "name": "Filipinho",
      "position": "ZAG",
      "rating": 78,
      "age": 24
    },
    {
      "name": "Gilberto Junior",
      "position": "ZAG",
      "rating": 78,
      "age": 21
    }
  ],
  "atletico_mg": [
    {
      "name": "Rômulo",
      "position": "ZAG",
      "rating": 83,
      "age": 22
    },
    {
      "name": "Kauã Pascini",
      "position": "ZAG",
      "rating": 83,
      "age": 18
    },
    {
      "name": "Tomás Pérez",
      "position": "MEI",
      "rating": 83,
      "age": 20
    },
    {
      "name": "Renan Lodi",
      "position": "ZAG",
      "rating": 82,
      "age": 28
    },
    {
      "name": "Victor Hugo",
      "position": "MEI",
      "rating": 82,
      "age": 22
    },
    {
      "name": "Patrick Silva",
      "position": "MEI",
      "rating": 82,
      "age": 22
    },
    {
      "name": "Riquelme Henrique",
      "position": "ATA",
      "rating": 82,
      "age": 17
    },
    {
      "name": "Lyanco",
      "position": "ZAG",
      "rating": 81,
      "age": 29
    },
    {
      "name": "Mateo Casierra",
      "position": "ATA",
      "rating": 81,
      "age": 29
    },
    {
      "name": "Alan Minda",
      "position": "ATA",
      "rating": 81,
      "age": 23
    },
    {
      "name": "Lucas Louback",
      "position": "ATA",
      "rating": 81,
      "age": 20
    },
    {
      "name": "Wallysson Da Silva",
      "position": "ATA",
      "rating": 81,
      "age": 18
    },
    {
      "name": "Alexsander",
      "position": "MEI",
      "rating": 80,
      "age": 22
    },
    {
      "name": "Eric",
      "position": "MEI",
      "rating": 80,
      "age": 20
    },
    {
      "name": "Cauã Soares",
      "position": "ATA",
      "rating": 80,
      "age": 18
    },
    {
      "name": "Éverson",
      "position": "GOL",
      "rating": 79,
      "age": 35
    },
    {
      "name": "Gabriel Delfim",
      "position": "GOL",
      "rating": 79,
      "age": 24
    },
    {
      "name": "Samuel Barros",
      "position": "ZAG",
      "rating": 79,
      "age": 20
    },
    {
      "name": "Wanderson Junior De Souza Vaz",
      "position": "ZAG",
      "rating": 79,
      "age": 18
    },
    {
      "name": "Alan Franco",
      "position": "MEI",
      "rating": 79,
      "age": 27
    },
    {
      "name": "Tomás Cuello",
      "position": "ATA",
      "rating": 79,
      "age": 26
    },
    {
      "name": "Murillo Fernandes",
      "position": "ATA",
      "rating": 79,
      "age": 19
    },
    {
      "name": "Pedro Cobra",
      "position": "GOL",
      "rating": 78,
      "age": 20
    },
    {
      "name": "Kaio",
      "position": "GOL",
      "rating": 78,
      "age": 18
    }
  ],
  "bahia": [
    {
      "name": "Fabio",
      "position": "GOL",
      "rating": 83,
      "age": 18
    },
    {
      "name": "Ruan Pablo",
      "position": "ATA",
      "rating": 83,
      "age": 17
    },
    {
      "name": "Caio Suassuna",
      "position": "ATA",
      "rating": 83,
      "age": 19
    },
    {
      "name": "Ronaldo",
      "position": "GOL",
      "rating": 82,
      "age": 29
    },
    {
      "name": "Marcos Victor",
      "position": "ZAG",
      "rating": 82,
      "age": 24
    },
    {
      "name": "Zé Guilherme",
      "position": "ZAG",
      "rating": 82,
      "age": 21
    },
    {
      "name": "Rodrigo Nestor",
      "position": "MEI",
      "rating": 82,
      "age": 25
    },
    {
      "name": "Iuri Jean Carlo Neres Dos Santos",
      "position": "GOL",
      "rating": 81,
      "age": 26
    },
    {
      "name": "Caio Alexandre",
      "position": "MEI",
      "rating": 81,
      "age": 27
    },
    {
      "name": "João Coni",
      "position": "ATA",
      "rating": 81,
      "age": 20
    },
    {
      "name": "Léo",
      "position": "GOL",
      "rating": 80,
      "age": 35
    },
    {
      "name": "Dell",
      "position": "ATA",
      "rating": 80,
      "age": 18
    },
    {
      "name": "David Duarte",
      "position": "ZAG",
      "rating": 79,
      "age": 31
    },
    {
      "name": "Kanu",
      "position": "ZAG",
      "rating": 79,
      "age": 29
    },
    {
      "name": "Dodô",
      "position": "ZAG",
      "rating": 79,
      "age": 20
    },
    {
      "name": "Éverton Ribeiro",
      "position": "MEI",
      "rating": 79,
      "age": 37
    },
    {
      "name": "Erick",
      "position": "MEI",
      "rating": 79,
      "age": 28
    },
    {
      "name": "Sidney",
      "position": "MEI",
      "rating": 79,
      "age": 20
    },
    {
      "name": "Cristian Olivera",
      "position": "ATA",
      "rating": 79,
      "age": 24
    },
    {
      "name": "Willian José",
      "position": "ATA",
      "rating": 79,
      "age": 34
    },
    {
      "name": "Ryan Nascimento",
      "position": "ATA",
      "rating": 79,
      "age": 17
    },
    {
      "name": "Fredi Lippert",
      "position": "ZAG",
      "rating": 78,
      "age": 20
    },
    {
      "name": "Jean Lucas",
      "position": "MEI",
      "rating": 78,
      "age": 28
    },
    {
      "name": "Nicolás Acevedo",
      "position": "MEI",
      "rating": 78,
      "age": 27
    }
  ],
  "botafogo": [
    {
      "name": "Raul",
      "position": "GOL",
      "rating": 83,
      "age": 28
    },
    {
      "name": "Anthony",
      "position": "ZAG",
      "rating": 83,
      "age": 21
    },
    {
      "name": "Allan",
      "position": "MEI",
      "rating": 83,
      "age": 35
    },
    {
      "name": "Edenilson",
      "position": "MEI",
      "rating": 83,
      "age": 36
    },
    {
      "name": "Danilo Santos",
      "position": "MEI",
      "rating": 83,
      "age": 25
    },
    {
      "name": "Wallace Davi",
      "position": "MEI",
      "rating": 83,
      "age": 19
    },
    {
      "name": "Felipe Januário",
      "position": "ATA",
      "rating": 83,
      "age": 19
    },
    {
      "name": "Cristian Medina",
      "position": "MEI",
      "rating": 82,
      "age": 24
    },
    {
      "name": "Jordan Barrera",
      "position": "MEI",
      "rating": 82,
      "age": 20
    },
    {
      "name": "Lucas Villalba",
      "position": "ZAG",
      "rating": 82,
      "age": 31
    },
    {
      "name": "Caio Roque",
      "position": "ZAG",
      "rating": 81,
      "age": 24
    },
    {
      "name": "Newton",
      "position": "MEI",
      "rating": 81,
      "age": 26
    },
    {
      "name": "Caio Valle",
      "position": "MEI",
      "rating": 81,
      "age": 18
    },
    {
      "name": "Kauan Toledo",
      "position": "MEI",
      "rating": 81,
      "age": 20
    },
    {
      "name": "Alex Telles",
      "position": "ZAG",
      "rating": 80,
      "age": 33
    },
    {
      "name": "Kaio",
      "position": "ZAG",
      "rating": 80,
      "age": 30
    },
    {
      "name": "Nahuel Ferraresi",
      "position": "ZAG",
      "rating": 80,
      "age": 27
    },
    {
      "name": "Jhoan Hernández",
      "position": "ZAG",
      "rating": 80,
      "age": 20
    },
    {
      "name": "Ythallo",
      "position": "ZAG",
      "rating": 80,
      "age": 21
    },
    {
      "name": "Kauã Serafim",
      "position": "ZAG",
      "rating": 80,
      "age": 19
    },
    {
      "name": "Kayke",
      "position": "ATA",
      "rating": 79,
      "age": 20
    },
    {
      "name": "Fernando Marçal",
      "position": "ZAG",
      "rating": 79,
      "age": 37
    },
    {
      "name": "Vitinho",
      "position": "ZAG",
      "rating": 79,
      "age": 26
    },
    {
      "name": "Gabriel Da Silva Abdias",
      "position": "ZAG",
      "rating": 79,
      "age": 20
    }
  ],
  "chapecoense": [
    {
      "name": "Anderson Paixão",
      "position": "GOL",
      "rating": 83,
      "age": 28
    },
    {
      "name": "Kainã",
      "position": "GOL",
      "rating": 83,
      "age": 21
    },
    {
      "name": "Gustavo Talles",
      "position": "ZAG",
      "rating": 83,
      "age": 23
    },
    {
      "name": "Da Silva",
      "position": "ZAG",
      "rating": 83,
      "age": 26
    },
    {
      "name": "Kauan Godoy",
      "position": "MEI",
      "rating": 83,
      "age": 19
    },
    {
      "name": "Luizão",
      "position": "ATA",
      "rating": 83,
      "age": 20
    },
    {
      "name": "Bruno Pacheco",
      "position": "ZAG",
      "rating": 82,
      "age": 34
    },
    {
      "name": "Camilo",
      "position": "MEI",
      "rating": 82,
      "age": 27
    },
    {
      "name": "João Vitor",
      "position": "MEI",
      "rating": 82,
      "age": 28
    },
    {
      "name": "Maurício Garcez",
      "position": "ATA",
      "rating": 82,
      "age": 29
    },
    {
      "name": "João Henrique Araújo Bom",
      "position": "ATA",
      "rating": 82,
      "age": 21
    },
    {
      "name": "Walter Clar",
      "position": "ZAG",
      "rating": 81,
      "age": 31
    },
    {
      "name": "Rafael Thyere",
      "position": "ZAG",
      "rating": 81,
      "age": 33
    },
    {
      "name": "Eduardo",
      "position": "ZAG",
      "rating": 81,
      "age": 20
    },
    {
      "name": "Rubens Tadeu Hartmann Ricoldi",
      "position": "MEI",
      "rating": 81,
      "age": 23
    },
    {
      "name": "Marcinho",
      "position": "ATA",
      "rating": 81,
      "age": 31
    },
    {
      "name": "Bruno Leonardo",
      "position": "ZAG",
      "rating": 80,
      "age": 30
    },
    {
      "name": "Marcos Vinicius",
      "position": "ZAG",
      "rating": 80,
      "age": 29
    },
    {
      "name": "Everton",
      "position": "ZAG",
      "rating": 80,
      "age": 31
    },
    {
      "name": "Higor Matheus Meritão",
      "position": "MEI",
      "rating": 80,
      "age": 32
    },
    {
      "name": "Vinicius Eduardo De Almeida Gomes Da Silva",
      "position": "ZAG",
      "rating": 79,
      "age": 21
    },
    {
      "name": "Iago",
      "position": "ZAG",
      "rating": 79,
      "age": 19
    },
    {
      "name": "Márcio Kalebe",
      "position": "ZAG",
      "rating": 79,
      "age": 19
    },
    {
      "name": "David",
      "position": "MEI",
      "rating": 79,
      "age": 20
    }
  ],
  "corinthians": [
    {
      "name": "Matheus Bidu",
      "position": "ZAG",
      "rating": 83,
      "age": 27
    },
    {
      "name": "Matheus Pereira",
      "position": "MEI",
      "rating": 83,
      "age": 30
    },
    {
      "name": "Charles",
      "position": "MEI",
      "rating": 83,
      "age": 30
    },
    {
      "name": "Vitinho",
      "position": "MEI",
      "rating": 83,
      "age": 19
    },
    {
      "name": "Kaio",
      "position": "ATA",
      "rating": 83,
      "age": 22
    },
    {
      "name": "Kayke Ferrari",
      "position": "ATA",
      "rating": 83,
      "age": 22
    },
    {
      "name": "Hugo Souza",
      "position": "GOL",
      "rating": 82,
      "age": 27
    },
    {
      "name": "André Ramalho",
      "position": "ZAG",
      "rating": 82,
      "age": 34
    },
    {
      "name": "Guilherme Pellegrin Almeida",
      "position": "ZAG",
      "rating": 82,
      "age": 19
    },
    {
      "name": "Luiz Fabio",
      "position": "MEI",
      "rating": 82,
      "age": 19
    },
    {
      "name": "Fabrizio Angileri",
      "position": "ZAG",
      "rating": 81,
      "age": 32
    },
    {
      "name": "Mateuzinho",
      "position": "ZAG",
      "rating": 81,
      "age": 25
    },
    {
      "name": "Jacaré",
      "position": "ZAG",
      "rating": 81,
      "age": 19
    },
    {
      "name": "Caua Ribeiro",
      "position": "ZAG",
      "rating": 81,
      "age": 17
    },
    {
      "name": "Allan",
      "position": "MEI",
      "rating": 81,
      "age": 29
    },
    {
      "name": "André",
      "position": "MEI",
      "rating": 81,
      "age": 20
    },
    {
      "name": "Guilherme Caraguá",
      "position": "MEI",
      "rating": 81,
      "age": 19
    },
    {
      "name": "Memphis Depay",
      "position": "ATA",
      "rating": 81,
      "age": 32
    },
    {
      "name": "Vitinho",
      "position": "ATA",
      "rating": 81,
      "age": 32
    },
    {
      "name": "Pedro Raúl",
      "position": "ATA",
      "rating": 81,
      "age": 29
    },
    {
      "name": "Gustavo Milani",
      "position": "GOL",
      "rating": 80,
      "age": 17
    },
    {
      "name": "Gui Negão",
      "position": "ATA",
      "rating": 80,
      "age": 19
    },
    {
      "name": "João Pedro",
      "position": "ZAG",
      "rating": 79,
      "age": 22
    },
    {
      "name": "Luiz Eduardo",
      "position": "MEI",
      "rating": 79,
      "age": 19
    }
  ],
  "coritiba": [
    {
      "name": "Pedro Rangel",
      "position": "GOL",
      "rating": 83,
      "age": 26
    },
    {
      "name": "Benassi",
      "position": "GOL",
      "rating": 83,
      "age": 22
    },
    {
      "name": "Maicon",
      "position": "ZAG",
      "rating": 83,
      "age": 37
    },
    {
      "name": "Tiago",
      "position": "ZAG",
      "rating": 83,
      "age": 22
    },
    {
      "name": "João Almeida",
      "position": "ZAG",
      "rating": 83,
      "age": 20
    },
    {
      "name": "Josué Pesqueira",
      "position": "MEI",
      "rating": 83,
      "age": 35
    },
    {
      "name": "Fernando Sobral",
      "position": "MEI",
      "rating": 83,
      "age": 31
    },
    {
      "name": "Matheus Dias",
      "position": "ATA",
      "rating": 83,
      "age": 18
    },
    {
      "name": "Pedro Luccas",
      "position": "GOL",
      "rating": 82,
      "age": 22
    },
    {
      "name": "João Pedro Chermont",
      "position": "ZAG",
      "rating": 82,
      "age": 20
    },
    {
      "name": "Geovane Santana Meurer",
      "position": "MEI",
      "rating": 82,
      "age": 24
    },
    {
      "name": "Thiago Azaf",
      "position": "MEI",
      "rating": 82,
      "age": 19
    },
    {
      "name": "Renato Marques",
      "position": "ATA",
      "rating": 82,
      "age": 22
    },
    {
      "name": "Alejandro Ararat",
      "position": "MEI",
      "rating": 81,
      "age": 19
    },
    {
      "name": "Felipe Jonatan",
      "position": "ZAG",
      "rating": 80,
      "age": 28
    },
    {
      "name": "Wallison Luiz",
      "position": "MEI",
      "rating": 80,
      "age": 28
    },
    {
      "name": "Éberth",
      "position": "ATA",
      "rating": 79,
      "age": 23
    },
    {
      "name": "Gabriel Leite",
      "position": "GOL",
      "rating": 79,
      "age": 38
    },
    {
      "name": "Gustavo",
      "position": "MEI",
      "rating": 79,
      "age": 23
    },
    {
      "name": "Breno",
      "position": "ATA",
      "rating": 79,
      "age": 30
    },
    {
      "name": "Keiller",
      "position": "GOL",
      "rating": 78,
      "age": 29
    },
    {
      "name": "Rodrigo Moledo",
      "position": "ZAG",
      "rating": 78,
      "age": 38
    },
    {
      "name": "Tissi",
      "position": "MEI",
      "rating": 78,
      "age": 19
    },
    {
      "name": "Miguel Silva",
      "position": "MEI",
      "rating": 78,
      "age": 18
    }
  ],
  "cruzeiro": [
    {
      "name": "Cássio",
      "position": "GOL",
      "rating": 83,
      "age": 39
    },
    {
      "name": "Matheus Cunha Queiroz",
      "position": "GOL",
      "rating": 83,
      "age": 25
    },
    {
      "name": "João Marcelo",
      "position": "ZAG",
      "rating": 83,
      "age": 26
    },
    {
      "name": "Pedro Henrique Franklim Martins",
      "position": "ZAG",
      "rating": 83,
      "age": 22
    },
    {
      "name": "Murilo Rhikman",
      "position": "MEI",
      "rating": 83,
      "age": 20
    },
    {
      "name": "William",
      "position": "ZAG",
      "rating": 82,
      "age": 31
    },
    {
      "name": "Jonathan Jesus",
      "position": "ZAG",
      "rating": 82,
      "age": 22
    },
    {
      "name": "Gerson",
      "position": "MEI",
      "rating": 82,
      "age": 29
    },
    {
      "name": "Neyser Villareal",
      "position": "MEI",
      "rating": 82,
      "age": 21
    },
    {
      "name": "Keny Arroyo",
      "position": "ATA",
      "rating": 82,
      "age": 20
    },
    {
      "name": "Kaique Kenji",
      "position": "ATA",
      "rating": 82,
      "age": 20
    },
    {
      "name": "Danilo Gimenes",
      "position": "ATA",
      "rating": 82,
      "age": 19
    },
    {
      "name": "João Wellington",
      "position": "MEI",
      "rating": 81,
      "age": 22
    },
    {
      "name": "Fabrício Bruno",
      "position": "ZAG",
      "rating": 80,
      "age": 30
    },
    {
      "name": "Lucas Silva",
      "position": "MEI",
      "rating": 80,
      "age": 33
    },
    {
      "name": "Eduardo Pape",
      "position": "MEI",
      "rating": 80,
      "age": 17
    },
    {
      "name": "Marquinhos",
      "position": "ATA",
      "rating": 80,
      "age": 23
    },
    {
      "name": "Lucas Romero",
      "position": "MEI",
      "rating": 79,
      "age": 32
    },
    {
      "name": "Bruno Rodrigues",
      "position": "ATA",
      "rating": 79,
      "age": 29
    },
    {
      "name": "Wanderson",
      "position": "ATA",
      "rating": 78,
      "age": 31
    },
    {
      "name": "Pablo",
      "position": "ATA",
      "rating": 78,
      "age": 19
    },
    {
      "name": "Nicolas Pontes",
      "position": "ZAG",
      "rating": 77,
      "age": 20
    },
    {
      "name": "Kauã Moraes Silva",
      "position": "ZAG",
      "rating": 77,
      "age": 20
    },
    {
      "name": "Kelvin Coutinho",
      "position": "ZAG",
      "rating": 77,
      "age": 20
    }
  ],
  "flamengo": [
    {
      "name": "Gusttavo Sousa",
      "position": "ZAG",
      "rating": 83,
      "age": 20
    },
    {
      "name": "Daniel Carvalho Marinho Da Silva",
      "position": "ZAG",
      "rating": 83,
      "age": 17
    },
    {
      "name": "Jorginho",
      "position": "MEI",
      "rating": 83,
      "age": 34
    },
    {
      "name": "Erick Pulgar",
      "position": "MEI",
      "rating": 83,
      "age": 32
    },
    {
      "name": "Nicolás de la Cruz",
      "position": "MEI",
      "rating": 83,
      "age": 29
    },
    {
      "name": "Gonzalo Plata",
      "position": "ATA",
      "rating": 83,
      "age": 25
    },
    {
      "name": "Agustín Rossi",
      "position": "GOL",
      "rating": 82,
      "age": 30
    },
    {
      "name": "Andrew",
      "position": "GOL",
      "rating": 82,
      "age": 25
    },
    {
      "name": "Emerson Royal",
      "position": "ZAG",
      "rating": 82,
      "age": 27
    },
    {
      "name": "Jorge Carrascal",
      "position": "MEI",
      "rating": 82,
      "age": 28
    },
    {
      "name": "Rayan Lucas",
      "position": "MEI",
      "rating": 82,
      "age": 21
    },
    {
      "name": "João",
      "position": "ATA",
      "rating": 82,
      "age": 19
    },
    {
      "name": "Leó Nannetti",
      "position": "GOL",
      "rating": 81,
      "age": 18
    },
    {
      "name": "Guillermo Varela",
      "position": "ZAG",
      "rating": 81,
      "age": 33
    },
    {
      "name": "Léo Ortiz",
      "position": "ZAG",
      "rating": 81,
      "age": 30
    },
    {
      "name": "Guilherme Gomes",
      "position": "MEI",
      "rating": 81,
      "age": 20
    },
    {
      "name": "Luiz Felipe",
      "position": "MEI",
      "rating": 81,
      "age": 18
    },
    {
      "name": "Luiz Araújo",
      "position": "ATA",
      "rating": 81,
      "age": 30
    },
    {
      "name": "Gabriel Laizo  Werneck",
      "position": "GOL",
      "rating": 80,
      "age": 17
    },
    {
      "name": "Vitão",
      "position": "ZAG",
      "rating": 80,
      "age": 26
    },
    {
      "name": "Da Mata",
      "position": "ZAG",
      "rating": 80,
      "age": 20
    },
    {
      "name": "Johnny Monteiro Góes",
      "position": "ZAG",
      "rating": 80,
      "age": 19
    },
    {
      "name": "Lucas Paquetá",
      "position": "MEI",
      "rating": 80,
      "age": 28
    },
    {
      "name": "Jhefinho",
      "position": "MEI",
      "rating": 80,
      "age": 18
    }
  ],
  "fluminense": [
    {
      "name": "Fábio",
      "position": "GOL",
      "rating": 83,
      "age": 45
    },
    {
      "name": "Juan Freytes",
      "position": "ZAG",
      "rating": 83,
      "age": 26
    },
    {
      "name": "Davi Schuindt",
      "position": "ZAG",
      "rating": 83,
      "age": 22
    },
    {
      "name": "Agner",
      "position": "MEI",
      "rating": 83,
      "age": 21
    },
    {
      "name": "Paulo Guilherme",
      "position": "MEI",
      "rating": 83,
      "age": 18
    },
    {
      "name": "Lelê",
      "position": "ATA",
      "rating": 82,
      "age": 28
    },
    {
      "name": "René",
      "position": "ZAG",
      "rating": 82,
      "age": 33
    },
    {
      "name": "Julian Millan",
      "position": "ZAG",
      "rating": 82,
      "age": 28
    },
    {
      "name": "Jemmes",
      "position": "ZAG",
      "rating": 82,
      "age": 26
    },
    {
      "name": "Breno",
      "position": "ZAG",
      "rating": 82,
      "age": 19
    },
    {
      "name": "Gorgulho",
      "position": "ZAG",
      "rating": 82,
      "age": 19
    },
    {
      "name": "Otávio",
      "position": "MEI",
      "rating": 82,
      "age": 32
    },
    {
      "name": "Nonato",
      "position": "MEI",
      "rating": 82,
      "age": 28
    },
    {
      "name": "John Kennedy",
      "position": "ATA",
      "rating": 82,
      "age": 24
    },
    {
      "name": "Riquelme",
      "position": "ATA",
      "rating": 82,
      "age": 19
    },
    {
      "name": "Luciano Acosta",
      "position": "MEI",
      "rating": 81,
      "age": 32
    },
    {
      "name": "Matheus Reis",
      "position": "ATA",
      "rating": 81,
      "age": 19
    },
    {
      "name": "Isack Pelé",
      "position": "ATA",
      "rating": 81,
      "age": 19
    },
    {
      "name": "Enzo",
      "position": "ATA",
      "rating": 81,
      "age": 20
    },
    {
      "name": "Hulk",
      "position": "ATA",
      "rating": 80,
      "age": 39
    },
    {
      "name": "Guilherme Arana",
      "position": "ZAG",
      "rating": 80,
      "age": 29
    },
    {
      "name": "Igor Rabello",
      "position": "ZAG",
      "rating": 80,
      "age": 31
    },
    {
      "name": "Ignácio",
      "position": "ZAG",
      "rating": 80,
      "age": 29
    },
    {
      "name": "Ganso",
      "position": "MEI",
      "rating": 80,
      "age": 36
    }
  ],
  "gremio": [
    {
      "name": "Gabriel Grando",
      "position": "GOL",
      "rating": 83,
      "age": 26
    },
    {
      "name": "Fabián Balbuena",
      "position": "ZAG",
      "rating": 83,
      "age": 34
    },
    {
      "name": "Luis Eduardo",
      "position": "ZAG",
      "rating": 83,
      "age": 18
    },
    {
      "name": "Wálter Kannemann",
      "position": "ZAG",
      "rating": 82,
      "age": 35
    },
    {
      "name": "Dodi",
      "position": "MEI",
      "rating": 82,
      "age": 30
    },
    {
      "name": "Mathías Villasanti",
      "position": "MEI",
      "rating": 82,
      "age": 29
    },
    {
      "name": "Artur Junior",
      "position": "MEI",
      "rating": 82,
      "age": 19
    },
    {
      "name": "Lago Menezes",
      "position": "MEI",
      "rating": 82,
      "age": 17
    },
    {
      "name": "Martin Braithwaite",
      "position": "ATA",
      "rating": 82,
      "age": 35
    },
    {
      "name": "Weverton",
      "position": "GOL",
      "rating": 81,
      "age": 38
    },
    {
      "name": "Thiago Stallbaum",
      "position": "GOL",
      "rating": 81,
      "age": 23
    },
    {
      "name": "João Victor Castelo",
      "position": "GOL",
      "rating": 81,
      "age": 20
    },
    {
      "name": "Gabriel Menegon",
      "position": "GOL",
      "rating": 81,
      "age": 17
    },
    {
      "name": "Marcos Rocha",
      "position": "ZAG",
      "rating": 81,
      "age": 37
    },
    {
      "name": "Vagner",
      "position": "ZAG",
      "rating": 81,
      "age": 17
    },
    {
      "name": "Jeferson Forneck",
      "position": "MEI",
      "rating": 81,
      "age": 19
    },
    {
      "name": "José Enamorado",
      "position": "ATA",
      "rating": 81,
      "age": 27
    },
    {
      "name": "Mateus Tetê",
      "position": "ATA",
      "rating": 81,
      "age": 26
    },
    {
      "name": "João Pedro",
      "position": "ZAG",
      "rating": 80,
      "age": 29
    },
    {
      "name": "Gustavo Martins",
      "position": "ZAG",
      "rating": 80,
      "age": 23
    },
    {
      "name": "Leonel Pérez",
      "position": "MEI",
      "rating": 80,
      "age": 21
    },
    {
      "name": "Arnaldo",
      "position": "ATA",
      "rating": 80,
      "age": 19
    },
    {
      "name": "Adriel",
      "position": "GOL",
      "rating": 79,
      "age": 25
    },
    {
      "name": "João Borne",
      "position": "MEI",
      "rating": 79,
      "age": 18
    }
  ],
  "internacional": [
    {
      "name": "Diego Esser",
      "position": "GOL",
      "rating": 83,
      "age": 21
    },
    {
      "name": "Alexander Bernabei",
      "position": "ZAG",
      "rating": 83,
      "age": 25
    },
    {
      "name": "Pedro Kauã",
      "position": "ZAG",
      "rating": 83,
      "age": 20
    },
    {
      "name": "Luiz Felipe De Morais Francisco",
      "position": "ZAG",
      "rating": 83,
      "age": 26
    },
    {
      "name": "Bruno Henrique",
      "position": "MEI",
      "rating": 83,
      "age": 36
    },
    {
      "name": "Richard",
      "position": "MEI",
      "rating": 83,
      "age": 32
    },
    {
      "name": "João Victor",
      "position": "ATA",
      "rating": 83,
      "age": 18
    },
    {
      "name": "Denis Marfo",
      "position": "ZAG",
      "rating": 82,
      "age": 20
    },
    {
      "name": "Kayky Chagas",
      "position": "ATA",
      "rating": 82,
      "age": 23
    },
    {
      "name": "Thiago Maia",
      "position": "MEI",
      "rating": 81,
      "age": 29
    },
    {
      "name": "Rafael Borré",
      "position": "ATA",
      "rating": 81,
      "age": 30
    },
    {
      "name": "Johan Carbonero",
      "position": "ATA",
      "rating": 81,
      "age": 26
    },
    {
      "name": "Anthoni",
      "position": "GOL",
      "rating": 80,
      "age": 24
    },
    {
      "name": "Gabriel Mercado",
      "position": "ZAG",
      "rating": 80,
      "age": 39
    },
    {
      "name": "Victor Gabriel",
      "position": "ZAG",
      "rating": 80,
      "age": 22
    },
    {
      "name": "Alisson",
      "position": "ZAG",
      "rating": 80,
      "age": 17
    },
    {
      "name": "Allex",
      "position": "MEI",
      "rating": 80,
      "age": 20
    },
    {
      "name": "Bruno Tabata",
      "position": "ATA",
      "rating": 80,
      "age": 29
    },
    {
      "name": "Yago",
      "position": "ATA",
      "rating": 80,
      "age": 19
    },
    {
      "name": "Fabricio Prado",
      "position": "ATA",
      "rating": 80,
      "age": 26
    },
    {
      "name": "Juninho",
      "position": "ZAG",
      "rating": 79,
      "age": 31
    },
    {
      "name": "Brian Aguirre",
      "position": "ZAG",
      "rating": 79,
      "age": 25
    },
    {
      "name": "Ronaldo",
      "position": "MEI",
      "rating": 79,
      "age": 29
    },
    {
      "name": "Bruno Gomes",
      "position": "MEI",
      "rating": 79,
      "age": 25
    }
  ],
  "mirassol": [
    {
      "name": "Vinicius Bacchi De Castro",
      "position": "ATA",
      "rating": 83,
      "age": 19
    },
    {
      "name": "Felipe Pereira dos",
      "position": "ATA",
      "rating": 83,
      "age": 19
    },
    {
      "name": "Georgemy",
      "position": "GOL",
      "rating": 82,
      "age": 30
    },
    {
      "name": "Lucas Oliveira",
      "position": "ZAG",
      "rating": 82,
      "age": 30
    },
    {
      "name": "Denilson",
      "position": "MEI",
      "rating": 81,
      "age": 25
    },
    {
      "name": "Tiquinho Soares",
      "position": "ATA",
      "rating": 81,
      "age": 35
    },
    {
      "name": "Carlos Eduardo",
      "position": "ATA",
      "rating": 81,
      "age": 29
    },
    {
      "name": "Alex Muralha",
      "position": "GOL",
      "rating": 80,
      "age": 36
    },
    {
      "name": "Willian Machado",
      "position": "ZAG",
      "rating": 80,
      "age": 29
    },
    {
      "name": "Igor Marques",
      "position": "ZAG",
      "rating": 80,
      "age": 27
    },
    {
      "name": "Edson Carioca",
      "position": "ATA",
      "rating": 80,
      "age": 29
    },
    {
      "name": "Gabriel",
      "position": "ZAG",
      "rating": 79,
      "age": 18
    },
    {
      "name": "Reinaldo",
      "position": "ZAG",
      "rating": 79,
      "age": 36
    },
    {
      "name": "Daniel Borges",
      "position": "ZAG",
      "rating": 79,
      "age": 33
    },
    {
      "name": "Carlos Eduardo",
      "position": "MEI",
      "rating": 79,
      "age": 36
    },
    {
      "name": "André Luis",
      "position": "ATA",
      "rating": 79,
      "age": 32
    },
    {
      "name": "Alesson",
      "position": "ATA",
      "rating": 79,
      "age": 27
    },
    {
      "name": "Victor Luis",
      "position": "ZAG",
      "rating": 78,
      "age": 33
    },
    {
      "name": "Cauã Victor Soares Da Silva",
      "position": "ZAG",
      "rating": 78,
      "age": 17
    },
    {
      "name": "Neto Moura",
      "position": "MEI",
      "rating": 78,
      "age": 29
    },
    {
      "name": "Shaylon",
      "position": "MEI",
      "rating": 78,
      "age": 29
    },
    {
      "name": "Everton",
      "position": "ATA",
      "rating": 78,
      "age": 29
    },
    {
      "name": "Glaucon",
      "position": "ATA",
      "rating": 78,
      "age": 20
    },
    {
      "name": "Thomazella",
      "position": "GOL",
      "rating": 77,
      "age": 35
    }
  ],
  "palmeiras": [
    {
      "name": "Kauan Lima",
      "position": "GOL",
      "rating": 83,
      "age": 19
    },
    {
      "name": "Derick",
      "position": "ZAG",
      "rating": 83,
      "age": 18
    },
    {
      "name": "Luccas Ramon",
      "position": "ZAG",
      "rating": 83,
      "age": 17
    },
    {
      "name": "André Lucas",
      "position": "ZAG",
      "rating": 83,
      "age": 20
    },
    {
      "name": "Felipe Anderson",
      "position": "MEI",
      "rating": 83,
      "age": 33
    },
    {
      "name": "Isaac",
      "position": "MEI",
      "rating": 83,
      "age": 19
    },
    {
      "name": "Allan Andrade",
      "position": "ATA",
      "rating": 83,
      "age": 22
    },
    {
      "name": "Khellven",
      "position": "ZAG",
      "rating": 82,
      "age": 25
    },
    {
      "name": "Luis Saboia",
      "position": "ZAG",
      "rating": 82,
      "age": 19
    },
    {
      "name": "Jhon Arias",
      "position": "MEI",
      "rating": 82,
      "age": 28
    },
    {
      "name": "Rafael Coutinho",
      "position": "MEI",
      "rating": 82,
      "age": 20
    },
    {
      "name": "Luis Felipe",
      "position": "MEI",
      "rating": 82,
      "age": 18
    },
    {
      "name": "Ramón Sosa",
      "position": "ATA",
      "rating": 82,
      "age": 26
    },
    {
      "name": "Vitor Roque",
      "position": "ATA",
      "rating": 82,
      "age": 21
    },
    {
      "name": "Heittor",
      "position": "ATA",
      "rating": 82,
      "age": 18
    },
    {
      "name": "Marcelo Lomba",
      "position": "GOL",
      "rating": 81,
      "age": 39
    },
    {
      "name": "Luiz Fernando",
      "position": "GOL",
      "rating": 81,
      "age": 18
    },
    {
      "name": "Luiz Benedetti",
      "position": "ZAG",
      "rating": 81,
      "age": 20
    },
    {
      "name": "Larson",
      "position": "MEI",
      "rating": 81,
      "age": 21
    },
    {
      "name": "Erick Machado",
      "position": "MEI",
      "rating": 81,
      "age": 19
    },
    {
      "name": "Ruan Yago",
      "position": "MEI",
      "rating": 81,
      "age": 17
    },
    {
      "name": "Kauã",
      "position": "ATA",
      "rating": 81,
      "age": 17
    },
    {
      "name": "Carlos Miguel",
      "position": "GOL",
      "rating": 80,
      "age": 27
    },
    {
      "name": "Emiliano Martínez",
      "position": "MEI",
      "rating": 80,
      "age": 26
    }
  ],
  "santos": [
    {
      "name": "João Paulo",
      "position": "GOL",
      "rating": 83,
      "age": 31
    },
    {
      "name": "Zé Rafael",
      "position": "MEI",
      "rating": 83,
      "age": 33
    },
    {
      "name": "Kaio Ganga",
      "position": "ATA",
      "rating": 83,
      "age": 19
    },
    {
      "name": "Gonzalo Escobar",
      "position": "ZAG",
      "rating": 82,
      "age": 29
    },
    {
      "name": "Willian Arão",
      "position": "MEI",
      "rating": 82,
      "age": 34
    },
    {
      "name": "Thaciano",
      "position": "MEI",
      "rating": 82,
      "age": 31
    },
    {
      "name": "Álvaro Barreal",
      "position": "MEI",
      "rating": 82,
      "age": 25
    },
    {
      "name": "Gabriel Menino",
      "position": "MEI",
      "rating": 82,
      "age": 25
    },
    {
      "name": "Pepê Fermino",
      "position": "MEI",
      "rating": 82,
      "age": 19
    },
    {
      "name": "Kauan Barreto",
      "position": "MEI",
      "rating": 82,
      "age": 18
    },
    {
      "name": "Benjamín Rollheiser",
      "position": "ATA",
      "rating": 82,
      "age": 26
    },
    {
      "name": "Lautaro Díaz",
      "position": "ATA",
      "rating": 82,
      "age": 28
    },
    {
      "name": "João Victor Dos Santos Alves",
      "position": "ATA",
      "rating": 82,
      "age": 18
    },
    {
      "name": "João Pedro",
      "position": "GOL",
      "rating": 81,
      "age": 18
    },
    {
      "name": "João Ananias",
      "position": "ZAG",
      "rating": 81,
      "age": 19
    },
    {
      "name": "João Schmidt",
      "position": "MEI",
      "rating": 81,
      "age": 33
    },
    {
      "name": "Christian Oliva",
      "position": "MEI",
      "rating": 81,
      "age": 30
    },
    {
      "name": "Vinícius Rocha",
      "position": "MEI",
      "rating": 81,
      "age": 17
    },
    {
      "name": "Pedro Assis",
      "position": "ATA",
      "rating": 81,
      "age": 19
    },
    {
      "name": "Diogenes",
      "position": "GOL",
      "rating": 80,
      "age": 25
    },
    {
      "name": "Rodrigo Falcão",
      "position": "GOL",
      "rating": 80,
      "age": 21
    },
    {
      "name": "Arthur Vale",
      "position": "GOL",
      "rating": 80,
      "age": 17
    },
    {
      "name": "Igor",
      "position": "ZAG",
      "rating": 80,
      "age": 29
    },
    {
      "name": "Zé Ivaldo",
      "position": "ZAG",
      "rating": 80,
      "age": 29
    }
  ],
  "sao_paulo": [
    {
      "name": "Sabino",
      "position": "ZAG",
      "rating": 83,
      "age": 29
    },
    {
      "name": "Luciano",
      "position": "ATA",
      "rating": 83,
      "age": 33
    },
    {
      "name": "Ryan Francisco",
      "position": "ATA",
      "rating": 83,
      "age": 19
    },
    {
      "name": "João Pedro",
      "position": "GOL",
      "rating": 82,
      "age": 20
    },
    {
      "name": "Rafael Tolói",
      "position": "ZAG",
      "rating": 82,
      "age": 35
    },
    {
      "name": "Luis Osorio",
      "position": "ZAG",
      "rating": 82,
      "age": 19
    },
    {
      "name": "Damián Bobadilla",
      "position": "MEI",
      "rating": 82,
      "age": 25
    },
    {
      "name": "Felipe Negrucci",
      "position": "MEI",
      "rating": 82,
      "age": 22
    },
    {
      "name": "Juan Potes",
      "position": "ATA",
      "rating": 82,
      "age": 19
    },
    {
      "name": "Rafael",
      "position": "GOL",
      "rating": 81,
      "age": 37
    },
    {
      "name": "Carlos Coronel",
      "position": "GOL",
      "rating": 81,
      "age": 29
    },
    {
      "name": "Felipe Preis",
      "position": "GOL",
      "rating": 81,
      "age": 20
    },
    {
      "name": "Wendell",
      "position": "ZAG",
      "rating": 81,
      "age": 32
    },
    {
      "name": "Igão",
      "position": "ZAG",
      "rating": 81,
      "age": 18
    },
    {
      "name": "Nicolas",
      "position": "ZAG",
      "rating": 81,
      "age": 19
    },
    {
      "name": "Luan",
      "position": "MEI",
      "rating": 81,
      "age": 27
    },
    {
      "name": "Gonzalo Tapia",
      "position": "ATA",
      "rating": 80,
      "age": 24
    },
    {
      "name": "Hugo",
      "position": "ZAG",
      "rating": 80,
      "age": 22
    },
    {
      "name": "Robert William",
      "position": "MEI",
      "rating": 80,
      "age": 16
    },
    {
      "name": "Guilherme Reis",
      "position": "ZAG",
      "rating": 79,
      "age": 20
    },
    {
      "name": "Djhordney Ferreira",
      "position": "MEI",
      "rating": 79,
      "age": 19
    },
    {
      "name": "Matheus Souza",
      "position": "ZAG",
      "rating": 78,
      "age": 23
    },
    {
      "name": "Danielzinho",
      "position": "MEI",
      "rating": 78,
      "age": 31
    },
    {
      "name": "Gustavo Santana",
      "position": "MEI",
      "rating": 78,
      "age": 20
    }
  ],
  "vasco": [
    {
      "name": "Daniel Fuzato",
      "position": "GOL",
      "rating": 83,
      "age": 29
    },
    {
      "name": "Pablo",
      "position": "GOL",
      "rating": 83,
      "age": 23
    },
    {
      "name": "José Luis Rodríguez",
      "position": "ZAG",
      "rating": 83,
      "age": 29
    },
    {
      "name": "Lucas Freitas",
      "position": "ZAG",
      "rating": 83,
      "age": 25
    },
    {
      "name": "Nuno Moreira",
      "position": "MEI",
      "rating": 83,
      "age": 27
    },
    {
      "name": "Cauan Barros",
      "position": "MEI",
      "rating": 83,
      "age": 22
    },
    {
      "name": "David",
      "position": "ATA",
      "rating": 83,
      "age": 30
    },
    {
      "name": "Marino Hinestroza",
      "position": "ATA",
      "rating": 83,
      "age": 24
    },
    {
      "name": "Melim",
      "position": "ZAG",
      "rating": 82,
      "age": 18
    },
    {
      "name": "Breno Sales",
      "position": "ZAG",
      "rating": 82,
      "age": 16
    },
    {
      "name": "Jair",
      "position": "MEI",
      "rating": 82,
      "age": 31
    },
    {
      "name": "Lucca Guima",
      "position": "MEI",
      "rating": 82,
      "age": 20
    },
    {
      "name": "Loide",
      "position": "ATA",
      "rating": 81,
      "age": 26
    },
    {
      "name": "Marcão",
      "position": "GOL",
      "rating": 81,
      "age": 20
    },
    {
      "name": "Lukas Zuccarello",
      "position": "MEI",
      "rating": 81,
      "age": 19
    },
    {
      "name": "Riquelme",
      "position": "ZAG",
      "rating": 80,
      "age": 23
    },
    {
      "name": "Walace",
      "position": "ZAG",
      "rating": 80,
      "age": 21
    },
    {
      "name": "Wanyson Nogueira",
      "position": "ZAG",
      "rating": 80,
      "age": 20
    },
    {
      "name": "Thiago Mendes",
      "position": "MEI",
      "rating": 80,
      "age": 34
    },
    {
      "name": "Bruno Lopes",
      "position": "ATA",
      "rating": 80,
      "age": 18
    },
    {
      "name": "Robert",
      "position": "ZAG",
      "rating": 79,
      "age": 22
    },
    {
      "name": "Matheus Carvalho",
      "position": "MEI",
      "rating": 79,
      "age": 24
    },
    {
      "name": "Claudio Spinelli",
      "position": "ATA",
      "rating": 79,
      "age": 29
    },
    {
      "name": "Diego Minete",
      "position": "ATA",
      "rating": 79,
      "age": 17
    }
  ],
  "vitoria": [
    {
      "name": "Claudinho",
      "position": "ZAG",
      "rating": 83,
      "age": 25
    },
    {
      "name": "Guilherme Inácio",
      "position": "ZAG",
      "rating": 83,
      "age": 18
    },
    {
      "name": "Marcos Vinicius",
      "position": "ATA",
      "rating": 83,
      "age": 19
    },
    {
      "name": "Cacá",
      "position": "ZAG",
      "rating": 82,
      "age": 27
    },
    {
      "name": "Fabiano",
      "position": "ZAG",
      "rating": 82,
      "age": 26
    },
    {
      "name": "Kauan Santos",
      "position": "ZAG",
      "rating": 82,
      "age": 19
    },
    {
      "name": "Matheus",
      "position": "MEI",
      "rating": 82,
      "age": 28
    },
    {
      "name": "Alejandro Almaraz",
      "position": "MEI",
      "rating": 82,
      "age": 19
    },
    {
      "name": "Osvaldo",
      "position": "ATA",
      "rating": 82,
      "age": 39
    },
    {
      "name": "Ruan Gabriel",
      "position": "ATA",
      "rating": 82,
      "age": 18
    },
    {
      "name": "Luan Cândido",
      "position": "ZAG",
      "rating": 81,
      "age": 25
    },
    {
      "name": "Camutanga",
      "position": "ZAG",
      "rating": 81,
      "age": 32
    },
    {
      "name": "Nathan",
      "position": "ZAG",
      "rating": 81,
      "age": 23
    },
    {
      "name": "Pablo",
      "position": "MEI",
      "rating": 81,
      "age": 22
    },
    {
      "name": "Lucas Lohan",
      "position": "MEI",
      "rating": 81,
      "age": 20
    },
    {
      "name": "Diego Tarzia",
      "position": "ZAG",
      "rating": 80,
      "age": 23
    },
    {
      "name": "Enrique Saverio",
      "position": "MEI",
      "rating": 80,
      "age": 27
    },
    {
      "name": "Renato Kayzer",
      "position": "ATA",
      "rating": 80,
      "age": 30
    },
    {
      "name": "Ezequiel",
      "position": "GOL",
      "rating": 79,
      "age": 19
    },
    {
      "name": "Emmanuel Martínez",
      "position": "MEI",
      "rating": 79,
      "age": 32
    },
    {
      "name": "Gabriel",
      "position": "GOL",
      "rating": 78,
      "age": 33
    },
    {
      "name": "Lucas Arcanjo",
      "position": "GOL",
      "rating": 78,
      "age": 27
    },
    {
      "name": "Wanderson",
      "position": "ZAG",
      "rating": 78,
      "age": 17
    },
    {
      "name": "Ruben Ramos",
      "position": "ATA",
      "rating": 78,
      "age": 19
    }
  ],
  "america_mg": [
    {
      "name": "Eduardo Luiz Person",
      "position": "MEI",
      "rating": 74,
      "age": 29
    },
    {
      "name": "Luidy",
      "position": "ZAG",
      "rating": 73,
      "age": 17
    },
    {
      "name": "Gabriel Domingos",
      "position": "MEI",
      "rating": 73,
      "age": 25
    },
    {
      "name": "Yago Souza",
      "position": "MEI",
      "rating": 73,
      "age": 20
    },
    {
      "name": "Paulo Victor",
      "position": "ATA",
      "rating": 73,
      "age": 25
    },
    {
      "name": "Cássio",
      "position": "GOL",
      "rating": 72,
      "age": 24
    },
    {
      "name": "Heitor",
      "position": "ZAG",
      "rating": 72,
      "age": 22
    },
    {
      "name": "Jhonny Cardinoti Pedro",
      "position": "ZAG",
      "rating": 72,
      "age": 24
    },
    {
      "name": "Léo Alaba",
      "position": "ZAG",
      "rating": 72,
      "age": 27
    },
    {
      "name": "Rafael Barcelos",
      "position": "ZAG",
      "rating": 72,
      "age": 22
    },
    {
      "name": "Dalbert",
      "position": "ZAG",
      "rating": 71,
      "age": 32
    },
    {
      "name": "Otávio Gonçalves",
      "position": "MEI",
      "rating": 71,
      "age": 20
    },
    {
      "name": "Gabriel Oliveira Santos",
      "position": "MEI",
      "rating": 71,
      "age": 26
    },
    {
      "name": "Gonzalo Mastriani",
      "position": "ATA",
      "rating": 71,
      "age": 33
    },
    {
      "name": "Matías Segovia",
      "position": "ATA",
      "rating": 71,
      "age": 23
    },
    {
      "name": "Pedro Geovane Paranhos Santos",
      "position": "ATA",
      "rating": 71,
      "age": 19
    },
    {
      "name": "Italo Brito",
      "position": "GOL",
      "rating": 70,
      "age": 20
    },
    {
      "name": "Thallyson",
      "position": "ZAG",
      "rating": 70,
      "age": 20
    },
    {
      "name": "Alê",
      "position": "MEI",
      "rating": 70,
      "age": 36
    },
    {
      "name": "Kaique Zizero",
      "position": "MEI",
      "rating": 70,
      "age": 19
    },
    {
      "name": "Everton Sidnei De Brito",
      "position": "ATA",
      "rating": 70,
      "age": 31
    },
    {
      "name": "William",
      "position": "GOL",
      "rating": 69,
      "age": 28
    },
    {
      "name": "Ricardo Silva",
      "position": "ZAG",
      "rating": 69,
      "age": 33
    },
    {
      "name": "Wesley Augusto Henn Marth",
      "position": "ZAG",
      "rating": 69,
      "age": 26
    }
  ],
  "avai": [
    {
      "name": "Jefferson",
      "position": "ZAG",
      "rating": 74,
      "age": 23
    },
    {
      "name": "Wallison",
      "position": "ZAG",
      "rating": 74,
      "age": 24
    },
    {
      "name": "Zé Ricardo",
      "position": "MEI",
      "rating": 74,
      "age": 30
    },
    {
      "name": "Nicolás Cabral",
      "position": "ZAG",
      "rating": 73,
      "age": 26
    },
    {
      "name": "Joao Victor",
      "position": "ZAG",
      "rating": 73,
      "age": 25
    },
    {
      "name": "Vinicius",
      "position": "MEI",
      "rating": 73,
      "age": 19
    },
    {
      "name": "Thayllon",
      "position": "ATA",
      "rating": 73,
      "age": 19
    },
    {
      "name": "Daniel Penha",
      "position": "MEI",
      "rating": 72,
      "age": 27
    },
    {
      "name": "Paulo Vitor",
      "position": "MEI",
      "rating": 72,
      "age": 21
    },
    {
      "name": "Bilu",
      "position": "ATA",
      "rating": 72,
      "age": 27
    },
    {
      "name": "Tucão",
      "position": "ATA",
      "rating": 72,
      "age": 21
    },
    {
      "name": "Igor José Bohn",
      "position": "GOL",
      "rating": 71,
      "age": 30
    },
    {
      "name": "Wesley",
      "position": "ZAG",
      "rating": 71,
      "age": 26
    },
    {
      "name": "Douglas",
      "position": "ZAG",
      "rating": 71,
      "age": 25
    },
    {
      "name": "Otávio",
      "position": "GOL",
      "rating": 70,
      "age": 33
    },
    {
      "name": "Guilherme Aquino",
      "position": "ZAG",
      "rating": 70,
      "age": 22
    },
    {
      "name": "Del Piage",
      "position": "MEI",
      "rating": 70,
      "age": 26
    },
    {
      "name": "Leonardo",
      "position": "GOL",
      "rating": 69,
      "age": 20
    },
    {
      "name": "William Fernando",
      "position": "ZAG",
      "rating": 69,
      "age": 20
    },
    {
      "name": "Gabriel Simples",
      "position": "ZAG",
      "rating": 69,
      "age": 21
    },
    {
      "name": "Hyan",
      "position": "MEI",
      "rating": 69,
      "age": 22
    },
    {
      "name": "Isaías",
      "position": "ATA",
      "rating": 68,
      "age": 21
    },
    {
      "name": "Caio Brazil Fonseca",
      "position": "MEI",
      "rating": 67,
      "age": 26
    },
    {
      "name": "Leó Aragão",
      "position": "GOL",
      "rating": 67,
      "age": 24
    }
  ],
  "botafogo_sp": [
    {
      "name": "Jordan",
      "position": "GOL",
      "rating": 74,
      "age": 28
    },
    {
      "name": "Carlão",
      "position": "ZAG",
      "rating": 74,
      "age": 25
    },
    {
      "name": "Darlan",
      "position": "ZAG",
      "rating": 74,
      "age": 22
    },
    {
      "name": "Guilherme Queiroz",
      "position": "MEI",
      "rating": 74,
      "age": 36
    },
    {
      "name": "Yuri",
      "position": "MEI",
      "rating": 74,
      "age": 20
    },
    {
      "name": "Pedro Henrique Souza Do Nascimento",
      "position": "ZAG",
      "rating": 73,
      "age": 19
    },
    {
      "name": "Kelvin",
      "position": "MEI",
      "rating": 73,
      "age": 28
    },
    {
      "name": "Arthur Caike",
      "position": "ATA",
      "rating": 72,
      "age": 34
    },
    {
      "name": "Hebert Willian Badaró Oliveira",
      "position": "ZAG",
      "rating": 72,
      "age": 21
    },
    {
      "name": "Jonathan Lemos",
      "position": "ZAG",
      "rating": 71,
      "age": 33
    },
    {
      "name": "Matheus Sales",
      "position": "MEI",
      "rating": 71,
      "age": 31
    },
    {
      "name": "Ruan Pablo De Oliveira Romano",
      "position": "MEI",
      "rating": 71,
      "age": 20
    },
    {
      "name": "Thiago Moraes",
      "position": "MEI",
      "rating": 71,
      "age": 28
    },
    {
      "name": "Wesley Pinheiro",
      "position": "ATA",
      "rating": 71,
      "age": 25
    },
    {
      "name": "Márcio Maranhão",
      "position": "ATA",
      "rating": 71,
      "age": 27
    },
    {
      "name": "Wallace",
      "position": "ZAG",
      "rating": 70,
      "age": 31
    },
    {
      "name": "Penha",
      "position": "ZAG",
      "rating": 70,
      "age": 20
    },
    {
      "name": "Marco Antônio",
      "position": "MEI",
      "rating": 70,
      "age": 26
    },
    {
      "name": "Hugo",
      "position": "ATA",
      "rating": 70,
      "age": 26
    },
    {
      "name": "Vilar",
      "position": "ZAG",
      "rating": 69,
      "age": 26
    },
    {
      "name": "Everton Morelli",
      "position": "MEI",
      "rating": 69,
      "age": 28
    },
    {
      "name": "Willian",
      "position": "ATA",
      "rating": 68,
      "age": 21
    },
    {
      "name": "Victor Souza",
      "position": "ZAG",
      "rating": 68,
      "age": 25
    },
    {
      "name": "Ericson",
      "position": "ZAG",
      "rating": 68,
      "age": 27
    }
  ],
  "crb": [
    {
      "name": "Vitor Caetano",
      "position": "GOL",
      "rating": 74,
      "age": 27
    },
    {
      "name": "Cândido",
      "position": "GOL",
      "rating": 74,
      "age": 20
    },
    {
      "name": "Crystopher",
      "position": "MEI",
      "rating": 74,
      "age": 28
    },
    {
      "name": "Cauã Carvalho",
      "position": "MEI",
      "rating": 74,
      "age": 19
    },
    {
      "name": "Luis Vinicius Nunes Cavalcante",
      "position": "ATA",
      "rating": 74,
      "age": 27
    },
    {
      "name": "Ruy Marcos Levino De Oliveira",
      "position": "ZAG",
      "rating": 73,
      "age": 19
    },
    {
      "name": "Luizao",
      "position": "MEI",
      "rating": 73,
      "age": 28
    },
    {
      "name": "Rian",
      "position": "MEI",
      "rating": 73,
      "age": 19
    },
    {
      "name": "Luiz Phellype",
      "position": "ATA",
      "rating": 73,
      "age": 32
    },
    {
      "name": "Leonardo de Campos",
      "position": "ZAG",
      "rating": 72,
      "age": 34
    },
    {
      "name": "Lucas Lovat",
      "position": "ZAG",
      "rating": 72,
      "age": 29
    },
    {
      "name": "Joao Neto",
      "position": "ATA",
      "rating": 72,
      "age": 23
    },
    {
      "name": "Anthony Matheus",
      "position": "ATA",
      "rating": 72,
      "age": 19
    },
    {
      "name": "Matheus",
      "position": "GOL",
      "rating": 71,
      "age": 31
    },
    {
      "name": "Heitor Brissantt",
      "position": "ZAG",
      "rating": 71,
      "age": 19
    },
    {
      "name": "Danielzinho",
      "position": "MEI",
      "rating": 70,
      "age": 30
    },
    {
      "name": "Dadá",
      "position": "ATA",
      "rating": 70,
      "age": 29
    },
    {
      "name": "Hereda",
      "position": "ZAG",
      "rating": 69,
      "age": 27
    },
    {
      "name": "Lyncon",
      "position": "ZAG",
      "rating": 69,
      "age": 21
    },
    {
      "name": "Kevin",
      "position": "ZAG",
      "rating": 68,
      "age": 28
    },
    {
      "name": "Reverson",
      "position": "ZAG",
      "rating": 68,
      "age": 29
    },
    {
      "name": "Fábio Augusto Schirmann",
      "position": "ZAG",
      "rating": 68,
      "age": 29
    },
    {
      "name": "Maycon",
      "position": "ZAG",
      "rating": 68,
      "age": 20
    },
    {
      "name": "Fábio",
      "position": "GOL",
      "rating": 67,
      "age": 23
    }
  ],
  "ceara": [
    {
      "name": "Jorge Meurer",
      "position": "GOL",
      "rating": 74,
      "age": 25
    },
    {
      "name": "Gustavo Martins",
      "position": "GOL",
      "rating": 74,
      "age": 20
    },
    {
      "name": "Sanchez",
      "position": "ZAG",
      "rating": 74,
      "age": 30
    },
    {
      "name": "Pedro Esli",
      "position": "MEI",
      "rating": 74,
      "age": 19
    },
    {
      "name": "Janderson",
      "position": "ZAG",
      "rating": 73,
      "age": 20
    },
    {
      "name": "Matheuzinho",
      "position": "MEI",
      "rating": 73,
      "age": 28
    },
    {
      "name": "Bruno",
      "position": "GOL",
      "rating": 72,
      "age": 32
    },
    {
      "name": "Rafael Ramos",
      "position": "ZAG",
      "rating": 72,
      "age": 31
    },
    {
      "name": "Luiz Otavio",
      "position": "ZAG",
      "rating": 72,
      "age": 37
    },
    {
      "name": "Éder",
      "position": "ZAG",
      "rating": 72,
      "age": 31
    },
    {
      "name": "Alex",
      "position": "ZAG",
      "rating": 71,
      "age": 32
    },
    {
      "name": "Richardson",
      "position": "MEI",
      "rating": 71,
      "age": 34
    },
    {
      "name": "Juan Alano",
      "position": "ATA",
      "rating": 71,
      "age": 29
    },
    {
      "name": "Luiz Otávio",
      "position": "ZAG",
      "rating": 70,
      "age": 33
    },
    {
      "name": "Bryan",
      "position": "ZAG",
      "rating": 70,
      "age": 29
    },
    {
      "name": "Stanley Boateng",
      "position": "ZAG",
      "rating": 70,
      "age": 21
    },
    {
      "name": "Vinicius Uchella",
      "position": "ZAG",
      "rating": 70,
      "age": 20
    },
    {
      "name": "Vinicius",
      "position": "MEI",
      "rating": 70,
      "age": 25
    },
    {
      "name": "Matheus Andrade",
      "position": "MEI",
      "rating": 70,
      "age": 24
    },
    {
      "name": "Gabriel Amaral",
      "position": "ATA",
      "rating": 69,
      "age": 20
    },
    {
      "name": "Caio",
      "position": "MEI",
      "rating": 69,
      "age": 18
    },
    {
      "name": "João Gabriel",
      "position": "MEI",
      "rating": 69,
      "age": 20
    },
    {
      "name": "Ronald",
      "position": "ZAG",
      "rating": 68,
      "age": 26
    },
    {
      "name": "Aloísio",
      "position": "ZAG",
      "rating": 68,
      "age": 18
    }
  ],
  "criciuma": [
    {
      "name": "Ruan Rodrigues Carvalho",
      "position": "ZAG",
      "rating": 74,
      "age": 19
    },
    {
      "name": "Fellipe Mateus",
      "position": "MEI",
      "rating": 74,
      "age": 35
    },
    {
      "name": "Steven Nufour",
      "position": "MEI",
      "rating": 74,
      "age": 21
    },
    {
      "name": "Jhonata Robert",
      "position": "ATA",
      "rating": 74,
      "age": 26
    },
    {
      "name": "João Carlos",
      "position": "ATA",
      "rating": 74,
      "age": 25
    },
    {
      "name": "Alisson",
      "position": "GOL",
      "rating": 73,
      "age": 31
    },
    {
      "name": "Kauã Moroso",
      "position": "GOL",
      "rating": 73,
      "age": 22
    },
    {
      "name": "Léo Mana",
      "position": "ZAG",
      "rating": 73,
      "age": 22
    },
    {
      "name": "Fabricio",
      "position": "MEI",
      "rating": 73,
      "age": 20
    },
    {
      "name": "Airton",
      "position": "GOL",
      "rating": 72,
      "age": 32
    },
    {
      "name": "Marcinho",
      "position": "ZAG",
      "rating": 72,
      "age": 30
    },
    {
      "name": "Gui Lobo",
      "position": "MEI",
      "rating": 72,
      "age": 26
    },
    {
      "name": "Lucas Vinicius Bugs",
      "position": "MEI",
      "rating": 72,
      "age": 20
    },
    {
      "name": "Cauê",
      "position": "ATA",
      "rating": 72,
      "age": 23
    },
    {
      "name": "Lucas Soratto",
      "position": "GOL",
      "rating": 71,
      "age": 19
    },
    {
      "name": "Octávio Henrique",
      "position": "ZAG",
      "rating": 71,
      "age": 21
    },
    {
      "name": "Jean",
      "position": "MEI",
      "rating": 71,
      "age": 31
    },
    {
      "name": "Romarinho",
      "position": "ATA",
      "rating": 71,
      "age": 32
    },
    {
      "name": "César",
      "position": "ZAG",
      "rating": 70,
      "age": 33
    },
    {
      "name": "Luciano Castan",
      "position": "ZAG",
      "rating": 69,
      "age": 36
    },
    {
      "name": "Rodrigo",
      "position": "ZAG",
      "rating": 69,
      "age": 39
    },
    {
      "name": "Ronald",
      "position": "MEI",
      "rating": 69,
      "age": 29
    },
    {
      "name": "Sandry",
      "position": "MEI",
      "rating": 69,
      "age": 23
    },
    {
      "name": "Hiago",
      "position": "MEI",
      "rating": 68,
      "age": 20
    }
  ],
  "cuiaba": [
    {
      "name": "Luisão",
      "position": "ZAG",
      "rating": 74,
      "age": 21
    },
    {
      "name": "Kauan",
      "position": "MEI",
      "rating": 74,
      "age": 20
    },
    {
      "name": "Diodato",
      "position": "ATA",
      "rating": 73,
      "age": 18
    },
    {
      "name": "Jean",
      "position": "GOL",
      "rating": 73,
      "age": 25
    },
    {
      "name": "Pepê",
      "position": "MEI",
      "rating": 73,
      "age": 28
    },
    {
      "name": "Kauan",
      "position": "ATA",
      "rating": 73,
      "age": 20
    },
    {
      "name": "Lucas Moraes",
      "position": "GOL",
      "rating": 72,
      "age": 19
    },
    {
      "name": "Alan Empereur",
      "position": "ZAG",
      "rating": 72,
      "age": 32
    },
    {
      "name": "Marlon Lopes",
      "position": "ZAG",
      "rating": 72,
      "age": 32
    },
    {
      "name": "Oscar",
      "position": "ZAG",
      "rating": 72,
      "age": 18
    },
    {
      "name": "Otávio",
      "position": "MEI",
      "rating": 72,
      "age": 29
    },
    {
      "name": "Rodrigo",
      "position": "ATA",
      "rating": 72,
      "age": 26
    },
    {
      "name": "Aiyran",
      "position": "ATA",
      "rating": 72,
      "age": 17
    },
    {
      "name": "João Carlos",
      "position": "GOL",
      "rating": 71,
      "age": 38
    },
    {
      "name": "João Chaves",
      "position": "GOL",
      "rating": 71,
      "age": 17
    },
    {
      "name": "Gabriel Knesowitsch",
      "position": "ZAG",
      "rating": 71,
      "age": 22
    },
    {
      "name": "Wesley Dias",
      "position": "MEI",
      "rating": 71,
      "age": 31
    },
    {
      "name": "Raul",
      "position": "MEI",
      "rating": 70,
      "age": 30
    },
    {
      "name": "Weverson",
      "position": "MEI",
      "rating": 70,
      "age": 22
    },
    {
      "name": "Calebe",
      "position": "MEI",
      "rating": 70,
      "age": 23
    },
    {
      "name": "Jean Dias",
      "position": "ATA",
      "rating": 69,
      "age": 35
    },
    {
      "name": "Pedro",
      "position": "ATA",
      "rating": 69,
      "age": 29
    },
    {
      "name": "Derik Lacerda",
      "position": "ATA",
      "rating": 69,
      "age": 26
    },
    {
      "name": "Railan",
      "position": "MEI",
      "rating": 69,
      "age": 26
    }
  ],
  "fortaleza": [
    {
      "name": "Lucca",
      "position": "MEI",
      "rating": 74,
      "age": 22
    },
    {
      "name": "Magrão",
      "position": "GOL",
      "rating": 73,
      "age": 26
    },
    {
      "name": "Guilherme",
      "position": "ZAG",
      "rating": 73,
      "age": 21
    },
    {
      "name": "Matheus Rossetto",
      "position": "MEI",
      "rating": 73,
      "age": 30
    },
    {
      "name": "Rodriguinho",
      "position": "MEI",
      "rating": 73,
      "age": 23
    },
    {
      "name": "Pierre",
      "position": "MEI",
      "rating": 72,
      "age": 24
    },
    {
      "name": "Rodrigo Santos",
      "position": "MEI",
      "rating": 72,
      "age": 25
    },
    {
      "name": "Gabriel",
      "position": "ATA",
      "rating": 72,
      "age": 21
    },
    {
      "name": "Bruninho",
      "position": "MEI",
      "rating": 71,
      "age": 21
    },
    {
      "name": "Tomás Roco",
      "position": "ATA",
      "rating": 71,
      "age": 20
    },
    {
      "name": "Brenno",
      "position": "GOL",
      "rating": 70,
      "age": 27
    },
    {
      "name": "Luan",
      "position": "ZAG",
      "rating": 70,
      "age": 25
    },
    {
      "name": "Paulo Ricardo",
      "position": "ZAG",
      "rating": 70,
      "age": 21
    },
    {
      "name": "Ryan",
      "position": "MEI",
      "rating": 70,
      "age": 23
    },
    {
      "name": "Welliton",
      "position": "ATA",
      "rating": 70,
      "age": 26
    },
    {
      "name": "João Ricardo",
      "position": "GOL",
      "rating": 69,
      "age": 37
    },
    {
      "name": "Tomás Cardona",
      "position": "ZAG",
      "rating": 69,
      "age": 30
    },
    {
      "name": "Ronald Falkoski",
      "position": "MEI",
      "rating": 69,
      "age": 23
    },
    {
      "name": "Kaua",
      "position": "ZAG",
      "rating": 68,
      "age": 19
    },
    {
      "name": "João Lucas",
      "position": "ZAG",
      "rating": 68,
      "age": 16
    },
    {
      "name": "Lucas Crispim",
      "position": "MEI",
      "rating": 68,
      "age": 32
    },
    {
      "name": "Calebe",
      "position": "MEI",
      "rating": 68,
      "age": 26
    },
    {
      "name": "Lucas Emanoel",
      "position": "ATA",
      "rating": 68,
      "age": 20
    },
    {
      "name": "Maílton dos Santos",
      "position": "ZAG",
      "rating": 67,
      "age": 28
    }
  ],
  "goias": [
    {
      "name": "Silva",
      "position": "ZAG",
      "rating": 74,
      "age": 31
    },
    {
      "name": "Juninho",
      "position": "MEI",
      "rating": 74,
      "age": 38
    },
    {
      "name": "Hygor",
      "position": "MEI",
      "rating": 74,
      "age": 17
    },
    {
      "name": "Ramon Menezes",
      "position": "ZAG",
      "rating": 73,
      "age": 31
    },
    {
      "name": "Jean Carlos Alves Ferreira",
      "position": "MEI",
      "rating": 73,
      "age": 21
    },
    {
      "name": "Luquinhas",
      "position": "MEI",
      "rating": 72,
      "age": 18
    },
    {
      "name": "Halerrandrio",
      "position": "ATA",
      "rating": 71,
      "age": 20
    },
    {
      "name": "Ezequiel",
      "position": "GOL",
      "rating": 71,
      "age": 23
    },
    {
      "name": "Rodrigo",
      "position": "ZAG",
      "rating": 71,
      "age": 33
    },
    {
      "name": "Murilo Camara",
      "position": "ZAG",
      "rating": 71,
      "age": 19
    },
    {
      "name": "Brayann",
      "position": "MEI",
      "rating": 71,
      "age": 28
    },
    {
      "name": "Pedrinho",
      "position": "ATA",
      "rating": 71,
      "age": 22
    },
    {
      "name": "Esli Garcia",
      "position": "ATA",
      "rating": 71,
      "age": 26
    },
    {
      "name": "Tadeu",
      "position": "GOL",
      "rating": 70,
      "age": 34
    },
    {
      "name": "Diego Caito",
      "position": "ZAG",
      "rating": 70,
      "age": 22
    },
    {
      "name": "Lourenco",
      "position": "MEI",
      "rating": 70,
      "age": 28
    },
    {
      "name": "Cadu",
      "position": "ATA",
      "rating": 70,
      "age": 22
    },
    {
      "name": "Kadu",
      "position": "ATA",
      "rating": 70,
      "age": 24
    },
    {
      "name": "Lucas Lima",
      "position": "MEI",
      "rating": 69,
      "age": 36
    },
    {
      "name": "Luiz Felipe",
      "position": "ZAG",
      "rating": 68,
      "age": 32
    },
    {
      "name": "Wellington Rato",
      "position": "MEI",
      "rating": 68,
      "age": 34
    },
    {
      "name": "Anselmo Ramon",
      "position": "ATA",
      "rating": 67,
      "age": 38
    },
    {
      "name": "Willie",
      "position": "ATA",
      "rating": 67,
      "age": 19
    },
    {
      "name": "Murillo Carvalho Victorio",
      "position": "GOL",
      "rating": 66,
      "age": 19
    }
  ],
  "juventude": [
    {
      "name": "Patryck",
      "position": "ZAG",
      "rating": 74,
      "age": 23
    },
    {
      "name": "Mateus Gabriel Schaffer",
      "position": "ZAG",
      "rating": 74,
      "age": 19
    },
    {
      "name": "Clébio",
      "position": "ZAG",
      "rating": 74,
      "age": 22
    },
    {
      "name": "Lucas Mineiro",
      "position": "MEI",
      "rating": 74,
      "age": 30
    },
    {
      "name": "Davi Goes",
      "position": "MEI",
      "rating": 74,
      "age": 21
    },
    {
      "name": "Marcos Paulo",
      "position": "ZAG",
      "rating": 73,
      "age": 23
    },
    {
      "name": "Luiz Eduardo",
      "position": "ZAG",
      "rating": 73,
      "age": 20
    },
    {
      "name": "Pedro",
      "position": "MEI",
      "rating": 73,
      "age": 20
    },
    {
      "name": "Nicolas Begliardi",
      "position": "MEI",
      "rating": 73,
      "age": 18
    },
    {
      "name": "Safira",
      "position": "ATA",
      "rating": 73,
      "age": 31
    },
    {
      "name": "João Victor Trevisol Da Silva",
      "position": "MEI",
      "rating": 72,
      "age": 21
    },
    {
      "name": "Luiz Henrique",
      "position": "MEI",
      "rating": 72,
      "age": 21
    },
    {
      "name": "Titi",
      "position": "ZAG",
      "rating": 71,
      "age": 38
    },
    {
      "name": "Pablo",
      "position": "MEI",
      "rating": 71,
      "age": 26
    },
    {
      "name": "Manuel Castro",
      "position": "ATA",
      "rating": 71,
      "age": 30
    },
    {
      "name": "Ray",
      "position": "ATA",
      "rating": 71,
      "age": 21
    },
    {
      "name": "Fábio Lima",
      "position": "ATA",
      "rating": 71,
      "age": 29
    },
    {
      "name": "Zé Henrique",
      "position": "GOL",
      "rating": 70,
      "age": 21
    },
    {
      "name": "Kaynan Fragoso Azevedo",
      "position": "MEI",
      "rating": 70,
      "age": 20
    },
    {
      "name": "Sasso",
      "position": "MEI",
      "rating": 70,
      "age": 20
    },
    {
      "name": "Léo Agliardi",
      "position": "GOL",
      "rating": 69,
      "age": 20
    },
    {
      "name": "Rodrigo Sam",
      "position": "ZAG",
      "rating": 69,
      "age": 30
    },
    {
      "name": "Gabriel",
      "position": "ZAG",
      "rating": 69,
      "age": 29
    },
    {
      "name": "Alan Kardec",
      "position": "ATA",
      "rating": 69,
      "age": 37
    }
  ],
  "londrina": [
    {
      "name": "Zanella",
      "position": "GOL",
      "rating": 74,
      "age": 22
    },
    {
      "name": "Gabriel Lacerda",
      "position": "ZAG",
      "rating": 74,
      "age": 26
    },
    {
      "name": "André Cardoso",
      "position": "MEI",
      "rating": 74,
      "age": 23
    },
    {
      "name": "Lucas Marques",
      "position": "MEI",
      "rating": 73,
      "age": 31
    },
    {
      "name": "João Vitor",
      "position": "MEI",
      "rating": 73,
      "age": 22
    },
    {
      "name": "Chumbinho",
      "position": "MEI",
      "rating": 73,
      "age": 22
    },
    {
      "name": "Caio Rafael",
      "position": "ATA",
      "rating": 73,
      "age": 22
    },
    {
      "name": "Caio Maia",
      "position": "ATA",
      "rating": 73,
      "age": 21
    },
    {
      "name": "Vitinho Mota",
      "position": "ATA",
      "rating": 73,
      "age": 22
    },
    {
      "name": "Luan",
      "position": "GOL",
      "rating": 72,
      "age": 29
    },
    {
      "name": "Yago Lincoln Rocha Santos",
      "position": "ZAG",
      "rating": 72,
      "age": 23
    },
    {
      "name": "Kauã Jonathan",
      "position": "ATA",
      "rating": 71,
      "age": 19
    },
    {
      "name": "Fabricio",
      "position": "ATA",
      "rating": 71,
      "age": 22
    },
    {
      "name": "Kevyn",
      "position": "ZAG",
      "rating": 70,
      "age": 28
    },
    {
      "name": "André Dhominique",
      "position": "ZAG",
      "rating": 70,
      "age": 22
    },
    {
      "name": "Thalis",
      "position": "MEI",
      "rating": 70,
      "age": 30
    },
    {
      "name": "Thiago",
      "position": "GOL",
      "rating": 69,
      "age": 19
    },
    {
      "name": "Caio",
      "position": "ZAG",
      "rating": 69,
      "age": 21
    },
    {
      "name": "Gilberto",
      "position": "ATA",
      "rating": 69,
      "age": 37
    },
    {
      "name": "Wallace Reis",
      "position": "ZAG",
      "rating": 68,
      "age": 38
    },
    {
      "name": "João Vitor",
      "position": "ZAG",
      "rating": 68,
      "age": 22
    },
    {
      "name": "Rafael Monteiro",
      "position": "ZAG",
      "rating": 68,
      "age": 22
    },
    {
      "name": "Asafe",
      "position": "ATA",
      "rating": 68,
      "age": 20
    },
    {
      "name": "Kauê Leonardo",
      "position": "ZAG",
      "rating": 67,
      "age": 21
    }
  ],
  "novorizontino": [
    {
      "name": "César",
      "position": "GOL",
      "rating": 74,
      "age": 31
    },
    {
      "name": "Miguel Contiero",
      "position": "MEI",
      "rating": 74,
      "age": 21
    },
    {
      "name": "Bruno Santana",
      "position": "MEI",
      "rating": 74,
      "age": 19
    },
    {
      "name": "Tavinho",
      "position": "ATA",
      "rating": 74,
      "age": 22
    },
    {
      "name": "Paulo Henrique Fagundes Dos Anjos",
      "position": "GOL",
      "rating": 73,
      "age": 35
    },
    {
      "name": "Luis",
      "position": "MEI",
      "rating": 73,
      "age": 29
    },
    {
      "name": "Ronald Barcellos",
      "position": "ATA",
      "rating": 73,
      "age": 24
    },
    {
      "name": "Eduardo Brock",
      "position": "ZAG",
      "rating": 72,
      "age": 35
    },
    {
      "name": "Alexis Alvariño",
      "position": "MEI",
      "rating": 72,
      "age": 25
    },
    {
      "name": "Sander",
      "position": "ZAG",
      "rating": 71,
      "age": 35
    },
    {
      "name": "Carlos Lora",
      "position": "ZAG",
      "rating": 71,
      "age": 25
    },
    {
      "name": "Carlinhos",
      "position": "ZAG",
      "rating": 71,
      "age": 31
    },
    {
      "name": "Gabriel Correia Da Silva",
      "position": "ZAG",
      "rating": 71,
      "age": 20
    },
    {
      "name": "Alemão",
      "position": "ZAG",
      "rating": 71,
      "age": 19
    },
    {
      "name": "Antony Gustavo Mariano Dos Santos",
      "position": "MEI",
      "rating": 71,
      "age": 21
    },
    {
      "name": "Jhones Kauê",
      "position": "MEI",
      "rating": 71,
      "age": 17
    },
    {
      "name": "Hector",
      "position": "ATA",
      "rating": 71,
      "age": 21
    },
    {
      "name": "Gabriel",
      "position": "ZAG",
      "rating": 70,
      "age": 27
    },
    {
      "name": "Arthur Barbosa",
      "position": "ZAG",
      "rating": 70,
      "age": 20
    },
    {
      "name": "Juninho",
      "position": "MEI",
      "rating": 70,
      "age": 25
    },
    {
      "name": "Jardiel",
      "position": "MEI",
      "rating": 70,
      "age": 21
    },
    {
      "name": "João Vitor Indalecio Scapin",
      "position": "GOL",
      "rating": 69,
      "age": 22
    },
    {
      "name": "Rômulo Simão",
      "position": "MEI",
      "rating": 69,
      "age": 24
    },
    {
      "name": "Christian Ortíz",
      "position": "MEI",
      "rating": 69,
      "age": 18
    }
  ],
  "nautico": [
    {
      "name": "Arthur Henrique Bittencourt",
      "position": "GOL",
      "rating": 74,
      "age": 29
    },
    {
      "name": "Gustavo Henrique Da Silva",
      "position": "ZAG",
      "rating": 74,
      "age": 20
    },
    {
      "name": "Betão",
      "position": "ZAG",
      "rating": 73,
      "age": 27
    },
    {
      "name": "Ramon",
      "position": "MEI",
      "rating": 73,
      "age": 29
    },
    {
      "name": "Felipe",
      "position": "ATA",
      "rating": 73,
      "age": 28
    },
    {
      "name": "Emanuel Minervino",
      "position": "ZAG",
      "rating": 72,
      "age": 17
    },
    {
      "name": "Leonai",
      "position": "MEI",
      "rating": 72,
      "age": 31
    },
    {
      "name": "Victor Andrade",
      "position": "ATA",
      "rating": 72,
      "age": 30
    },
    {
      "name": "Luiz Paulo",
      "position": "ZAG",
      "rating": 71,
      "age": 33
    },
    {
      "name": "Gabriel Índio",
      "position": "ZAG",
      "rating": 71,
      "age": 22
    },
    {
      "name": "Gledson",
      "position": "ZAG",
      "rating": 71,
      "age": 20
    },
    {
      "name": "Wenderson",
      "position": "MEI",
      "rating": 71,
      "age": 28
    },
    {
      "name": "Samuel",
      "position": "MEI",
      "rating": 71,
      "age": 22
    },
    {
      "name": "Felipe Redaelli",
      "position": "MEI",
      "rating": 71,
      "age": 23
    },
    {
      "name": "Reginaldo",
      "position": "ZAG",
      "rating": 70,
      "age": 33
    },
    {
      "name": "Luiz Felipe Oliveira De Paula",
      "position": "MEI",
      "rating": 70,
      "age": 28
    },
    {
      "name": "Halan",
      "position": "MEI",
      "rating": 70,
      "age": 20
    },
    {
      "name": "Paulo Sérgio",
      "position": "ATA",
      "rating": 70,
      "age": 37
    },
    {
      "name": "Isaque Ferreira",
      "position": "ATA",
      "rating": 70,
      "age": 19
    },
    {
      "name": "Muriel",
      "position": "GOL",
      "rating": 69,
      "age": 39
    },
    {
      "name": "Arnaldo",
      "position": "ZAG",
      "rating": 69,
      "age": 34
    },
    {
      "name": "Wanderson Camelo Viana",
      "position": "ZAG",
      "rating": 69,
      "age": 31
    },
    {
      "name": "Kevyn",
      "position": "ATA",
      "rating": 69,
      "age": 19
    },
    {
      "name": "Luiz Claudio",
      "position": "ATA",
      "rating": 69,
      "age": 21
    }
  ],
  "ponte_preta": [
    {
      "name": "Pedrinho",
      "position": "MEI",
      "rating": 74,
      "age": 18
    },
    {
      "name": "Miguel",
      "position": "MEI",
      "rating": 74,
      "age": 21
    },
    {
      "name": "Thalys Victor Martins Sena",
      "position": "ZAG",
      "rating": 73,
      "age": 26
    },
    {
      "name": "Gabriel Henrique",
      "position": "MEI",
      "rating": 73,
      "age": 20
    },
    {
      "name": "Guilherme Martins",
      "position": "MEI",
      "rating": 73,
      "age": 21
    },
    {
      "name": "Jonathan Cafú",
      "position": "ATA",
      "rating": 73,
      "age": 35
    },
    {
      "name": "João Victor Damião Dos Santos",
      "position": "ATA",
      "rating": 73,
      "age": 17
    },
    {
      "name": "Kevyson",
      "position": "ZAG",
      "rating": 72,
      "age": 22
    },
    {
      "name": "Gabriel",
      "position": "ZAG",
      "rating": 72,
      "age": 22
    },
    {
      "name": "Kawann",
      "position": "ZAG",
      "rating": 72,
      "age": 21
    },
    {
      "name": "Diego Tavares",
      "position": "ATA",
      "rating": 72,
      "age": 35
    },
    {
      "name": "Rodriguinho",
      "position": "ATA",
      "rating": 72,
      "age": 25
    },
    {
      "name": "Vinicius",
      "position": "GOL",
      "rating": 71,
      "age": 23
    },
    {
      "name": "Gustavo Teles",
      "position": "MEI",
      "rating": 71,
      "age": 21
    },
    {
      "name": "Vítor Ribeiro",
      "position": "ATA",
      "rating": 71,
      "age": 27
    },
    {
      "name": "Diogo Silva",
      "position": "GOL",
      "rating": 70,
      "age": 40
    },
    {
      "name": "João Gabriel",
      "position": "ZAG",
      "rating": 70,
      "age": 21
    },
    {
      "name": "Lucas Da Sliva Justen",
      "position": "ZAG",
      "rating": 70,
      "age": 23
    },
    {
      "name": "Tarik",
      "position": "MEI",
      "rating": 70,
      "age": 33
    },
    {
      "name": "Chicão",
      "position": "MEI",
      "rating": 70,
      "age": 18
    },
    {
      "name": "Diego Porfirio",
      "position": "ZAG",
      "rating": 69,
      "age": 26
    },
    {
      "name": "Gustavo Felipe Almeida",
      "position": "ZAG",
      "rating": 69,
      "age": 20
    },
    {
      "name": "Rodrigo Souza",
      "position": "MEI",
      "rating": 69,
      "age": 38
    },
    {
      "name": "André",
      "position": "MEI",
      "rating": 69,
      "age": 26
    }
  ],
  "sport": [
    {
      "name": "Dênis",
      "position": "GOL",
      "rating": 74,
      "age": 39
    },
    {
      "name": "Halls",
      "position": "GOL",
      "rating": 74,
      "age": 27
    },
    {
      "name": "Patrick",
      "position": "ZAG",
      "rating": 74,
      "age": 21
    },
    {
      "name": "José Gabriel",
      "position": "MEI",
      "rating": 74,
      "age": 27
    },
    {
      "name": "Gustavo Maia",
      "position": "ATA",
      "rating": 74,
      "age": 25
    },
    {
      "name": "Dedé",
      "position": "ATA",
      "rating": 74,
      "age": 20
    },
    {
      "name": "Arthur Moreira",
      "position": "ATA",
      "rating": 74,
      "age": 18
    },
    {
      "name": "Ze Marcos",
      "position": "ZAG",
      "rating": 73,
      "age": 28
    },
    {
      "name": "Felipinho",
      "position": "ZAG",
      "rating": 73,
      "age": 29
    },
    {
      "name": "Rafinha",
      "position": "ZAG",
      "rating": 73,
      "age": 20
    },
    {
      "name": "Zé Lucas",
      "position": "MEI",
      "rating": 73,
      "age": 18
    },
    {
      "name": "Pedro Perotti",
      "position": "ATA",
      "rating": 73,
      "age": 28
    },
    {
      "name": "Antônio Adriano",
      "position": "GOL",
      "rating": 72,
      "age": 23
    },
    {
      "name": "Adriel",
      "position": "MEI",
      "rating": 72,
      "age": 20
    },
    {
      "name": "Marlon",
      "position": "ATA",
      "rating": 72,
      "age": 28
    },
    {
      "name": "Micael",
      "position": "ATA",
      "rating": 72,
      "age": 20
    },
    {
      "name": "Lipão",
      "position": "ATA",
      "rating": 72,
      "age": 19
    },
    {
      "name": "Victor Hugo Barbosa De Farias",
      "position": "GOL",
      "rating": 70,
      "age": 20
    },
    {
      "name": "Richarlyson",
      "position": "ZAG",
      "rating": 70,
      "age": 18
    },
    {
      "name": "Biel",
      "position": "MEI",
      "rating": 70,
      "age": 24
    },
    {
      "name": "Habraão",
      "position": "ZAG",
      "rating": 69,
      "age": 25
    },
    {
      "name": "Felipinho Santos",
      "position": "MEI",
      "rating": 69,
      "age": 19
    },
    {
      "name": "Jefinho",
      "position": "ATA",
      "rating": 69,
      "age": 19
    },
    {
      "name": "Caio Moura",
      "position": "ZAG",
      "rating": 68,
      "age": 18
    }
  ],
  "sao_bernardo": [
    {
      "name": "Pará",
      "position": "ZAG",
      "rating": 74,
      "age": 30
    },
    {
      "name": "Lucas Rian Santos Oliveira",
      "position": "ATA",
      "rating": 74,
      "age": 26
    },
    {
      "name": "Alex Alves",
      "position": "GOL",
      "rating": 73,
      "age": 39
    },
    {
      "name": "Jemerson",
      "position": "ZAG",
      "rating": 73,
      "age": 33
    },
    {
      "name": "Helder Gomes Maciel",
      "position": "ZAG",
      "rating": 73,
      "age": 36
    },
    {
      "name": "Eduardo",
      "position": "MEI",
      "rating": 73,
      "age": 26
    },
    {
      "name": "Daniel Amorim",
      "position": "ATA",
      "rating": 73,
      "age": 36
    },
    {
      "name": "Hyoran",
      "position": "MEI",
      "rating": 72,
      "age": 33
    },
    {
      "name": "Kaká",
      "position": "MEI",
      "rating": 72,
      "age": 20
    },
    {
      "name": "Daniel Davi Simao Roque",
      "position": "ATA",
      "rating": 72,
      "age": 21
    },
    {
      "name": "Rodrigo Ferreira",
      "position": "ZAG",
      "rating": 71,
      "age": 31
    },
    {
      "name": "Hugo",
      "position": "ZAG",
      "rating": 71,
      "age": 32
    },
    {
      "name": "Pedrinho",
      "position": "ATA",
      "rating": 71,
      "age": 26
    },
    {
      "name": "Mário Sérgio",
      "position": "ZAG",
      "rating": 70,
      "age": 32
    },
    {
      "name": "Marcão Silva",
      "position": "MEI",
      "rating": 70,
      "age": 35
    },
    {
      "name": "Júnior Oliveira",
      "position": "GOL",
      "rating": 69,
      "age": 36
    },
    {
      "name": "Júnior Urso",
      "position": "MEI",
      "rating": 69,
      "age": 37
    },
    {
      "name": "Pedro Vitor",
      "position": "ATA",
      "rating": 69,
      "age": 28
    },
    {
      "name": "Neto Costa",
      "position": "ATA",
      "rating": 69,
      "age": 29
    },
    {
      "name": "Fabrício Daniel",
      "position": "ATA",
      "rating": 69,
      "age": 28
    },
    {
      "name": "Lino",
      "position": "MEI",
      "rating": 68,
      "age": 29
    },
    {
      "name": "Pablo Dyego",
      "position": "ATA",
      "rating": 68,
      "age": 32
    },
    {
      "name": "Echaporã",
      "position": "ATA",
      "rating": 68,
      "age": 26
    },
    {
      "name": "Matheus Nogueira",
      "position": "GOL",
      "rating": 67,
      "age": 28
    }
  ],
  "vila_nova": [
    {
      "name": "Breno Augusto De Azevedo Bora",
      "position": "MEI",
      "rating": 74,
      "age": 26
    },
    {
      "name": "Anderson Jesus",
      "position": "ZAG",
      "rating": 74,
      "age": 31
    },
    {
      "name": "Carlão",
      "position": "ZAG",
      "rating": 74,
      "age": 19
    },
    {
      "name": "Enzo",
      "position": "MEI",
      "rating": 74,
      "age": 23
    },
    {
      "name": "Soares",
      "position": "ATA",
      "rating": 73,
      "age": 20
    },
    {
      "name": "Samuel Lucas De Oliveira Souza",
      "position": "ZAG",
      "rating": 73,
      "age": 18
    },
    {
      "name": "Willian Maranhão",
      "position": "MEI",
      "rating": 73,
      "age": 30
    },
    {
      "name": "Dudu",
      "position": "MEI",
      "rating": 73,
      "age": 24
    },
    {
      "name": "Willian Prado Camargo",
      "position": "ZAG",
      "rating": 72,
      "age": 31
    },
    {
      "name": "Guilherme Vieira",
      "position": "MEI",
      "rating": 72,
      "age": 20
    },
    {
      "name": "Gabriel Dias",
      "position": "MEI",
      "rating": 72,
      "age": 17
    },
    {
      "name": "Dellatorre",
      "position": "ATA",
      "rating": 72,
      "age": 34
    },
    {
      "name": "Rafael Silva",
      "position": "ATA",
      "rating": 72,
      "age": 34
    },
    {
      "name": "Helton Leite",
      "position": "GOL",
      "rating": 71,
      "age": 35
    },
    {
      "name": "Gabriel Átila",
      "position": "GOL",
      "rating": 71,
      "age": 23
    },
    {
      "name": "Kauã",
      "position": "GOL",
      "rating": 70,
      "age": 19
    },
    {
      "name": "Gil",
      "position": "ZAG",
      "rating": 70,
      "age": 18
    },
    {
      "name": "Marquinhos Gabriel",
      "position": "MEI",
      "rating": 70,
      "age": 35
    },
    {
      "name": "Nathan",
      "position": "MEI",
      "rating": 70,
      "age": 20
    },
    {
      "name": "Ryan Lima",
      "position": "ATA",
      "rating": 70,
      "age": 25
    },
    {
      "name": "Tiago",
      "position": "ZAG",
      "rating": 69,
      "age": 36
    },
    {
      "name": "André Luis",
      "position": "ATA",
      "rating": 69,
      "age": 29
    },
    {
      "name": "Emerson Lima",
      "position": "ATA",
      "rating": 69,
      "age": 25
    },
    {
      "name": "Gustavo Puskas Pinheiro Lemos",
      "position": "ATA",
      "rating": 69,
      "age": 18
    }
  ]
}